shell_prompt/__init__.py
shell_prompt/__version__.py
shell_prompt/cli/__init__.py
shell_prompt/cli/main.py
shell_prompt/cli/parser.py
shell_prompt/config/__init__.py
shell_prompt/config/config_manager.py
shell_prompt/config/llm.py
shell_prompt/config/provider_data.py
shell_prompt-0.1.0.dist-info/METADATA
shell_prompt-0.1.0.dist-info/WHEEL
shell_prompt-0.1.0.dist-info/entry_points.txt
shell_prompt-0.1.0.dist-info/top_level.txt
shell_prompt-0.1.0.dist-info/RECORD
