Metadata-Version: 2.4
Name: shell-prompt
Version: 0.1.0
Summary: A command-line tool that converts natural language instructions into shell commands and executes them.
Home-page: https://github.com/082T/shell-prompt
Author: Roko Torbarina
Author-email: rokotorbarina9@gmail.com
License: MIT
Classifier: Programming Language :: Python :: 3
Classifier: License :: OSI Approved :: MIT License
Classifier: Operating System :: OS Independent
Requires-Dist: argparse
Provides-Extra: openai
Requires-Dist: langchain[openai]; extra == "openai"
Provides-Extra: anthropic
Requires-Dist: langchain[anthropic]; extra == "anthropic"
Provides-Extra: google-genai
Requires-Dist: langchain[google-genai]; extra == "google-genai"
Provides-Extra: groq
Requires-Dist: langchain[groq]; extra == "groq"
Provides-Extra: cohere
Requires-Dist: langchain[cohere]; extra == "cohere"
Provides-Extra: langchain-nvidia-ai-endpoints
Requires-Dist: langchain-nvidia-ai-endpoints; extra == "langchain-nvidia-ai-endpoints"
Provides-Extra: fireworks
Requires-Dist: langchain[fireworks]; extra == "fireworks"
Provides-Extra: mistralai
Requires-Dist: langchain[mistralai]; extra == "mistralai"
Provides-Extra: together
Requires-Dist: langchain[together]; extra == "together"
Provides-Extra: langchain-xai
Requires-Dist: langchain-xai; extra == "langchain-xai"
Provides-Extra: langchain-perplexity
Requires-Dist: langchain-perplexity; extra == "langchain-perplexity"
Dynamic: author
Dynamic: author-email
Dynamic: classifier
Dynamic: description
Dynamic: description-content-type
Dynamic: home-page
Dynamic: license
Dynamic: provides-extra
Dynamic: requires-dist
Dynamic: summary
